image_processing/__init__.py
image_processing/processing/__init__.py
image_processing/processing/combination.py
image_processing/processing/transformation.py
image_processing/utils/__init__.py
image_processing/utils/io.py
image_processing/utils/plot.py
Img_prcs_package-0.0.1.dist-info/METADATA
Img_prcs_package-0.0.1.dist-info/WHEEL
Img_prcs_package-0.0.1.dist-info/top_level.txt
Img_prcs_package-0.0.1.dist-info/RECORD
